sbc_drf_user/__init__.py
sbc_drf_user/apps.py
sbc_drf_user/errors.py
sbc_drf_user/factories.py
sbc_drf_user/models.py
sbc_drf_user/serializers.py
sbc_drf_user/signals.py
sbc_drf_user/tests.py
sbc_drf_user/urls.py
sbc_drf_user/views.py
sbc_drf_user/migrations/0001_initial.py
sbc_drf_user/migrations/__init__.py
sbc_drf_user-1.0.3.dist-info/LICENSE
sbc_drf_user-1.0.3.dist-info/METADATA
sbc_drf_user-1.0.3.dist-info/WHEEL
sbc_drf_user-1.0.3.dist-info/top_level.txt
sbc_drf_user-1.0.3.dist-info/zip-safe
sbc_drf_user-1.0.3.dist-info/RECORD
