Metadata-Version: 2.1
Name: sbc-drf-user
Version: 1.0.3
Summary: User app common SBC project.
Home-page: https://gitlab.stickboycreative.com/sbc-python/sbc_drf_user
Author: Abhinav Kotak
Author-email: in.abhi9@gmail.com
Maintainer: Abhinav Kotak
Maintainer-email: in.abhi9@gmail.com
License: MIT License
Requires-Dist: faker (==4.0.3)
